agentmd/__init__.py
agentmd/adapters.py
agentmd/agentmd.schema.json
agentmd/cli.py
agentmd/parse.py
agentmd/validate.py
agentmd-0.1.0.dist-info/METADATA
agentmd-0.1.0.dist-info/WHEEL
agentmd-0.1.0.dist-info/entry_points.txt
agentmd-0.1.0.dist-info/RECORD
