Metadata-Version: 2.1
Name: agentmd
Version: 0.1.0
Summary: CLI and library for the AGENT.md standard: schema-validated AI agent project guidelines
Project-URL: Homepage, https://github.com/rajanvijayan/agent.md
Project-URL: Repository, https://github.com/rajanvijayan/agent.md
Author: agent.md contributors
Keywords: AGENT.md,AGENTS.md,agent,ai,claude,copilot,cursor
Classifier: Development Status :: 3 - Alpha
Classifier: Intended Audience :: Developers
Classifier: License :: OSI Approved :: MIT License
Classifier: Programming Language :: Python :: 3
Classifier: Programming Language :: Python :: 3.10
Classifier: Programming Language :: Python :: 3.11
Classifier: Programming Language :: Python :: 3.12
Classifier: Topic :: Software Development
Requires-Python: >=3.10
Requires-Dist: jsonschema>=4.20
Requires-Dist: pyyaml>=6.0
Provides-Extra: dev
Requires-Dist: pytest-cov>=4.0; extra == 'dev'
Requires-Dist: pytest>=7.0; extra == 'dev'
